sicore/__init__.py
sicore/core/__init__.py
sicore/core/base.py
sicore/core/dist.py
sicore/core/real_subset.py
sicore/main/__init__.py
sicore/main/inference.py
sicore/utils/__init__.py
sicore/utils/constructor.py
sicore/utils/evaluation.py
sicore/utils/figure.py
sicore/utils/intervals.py
sicore/utils/non_gaussian.py
sicore/utils/uniformity_test.py
sicore-3.0.0.dist-info/METADATA
sicore-3.0.0.dist-info/WHEEL
sicore-3.0.0.dist-info/licenses/LICENSE.md
sicore-3.0.0.dist-info/RECORD
