Metadata-Version: 2.4
Name: sicore
Version: 3.0.0
Summary: Core Package for Selective Inference
Project-URL: documentation, https://shirara1016.github.io/sicore/
Project-URL: repository, https://github.com/shirara1016/sicore
Author: Takeuchi Lab
Maintainer-email: Tomohiro Shiraishi <shirara1016@gmail.com>
License-Expression: MIT
License-File: LICENSE.md
Classifier: License :: OSI Approved :: MIT License
Classifier: Programming Language :: Python :: 3.10
Classifier: Programming Language :: Python :: 3.11
Classifier: Programming Language :: Python :: 3.12
Classifier: Programming Language :: Python :: 3.13
Requires-Python: >=3.10
Requires-Dist: joblib>=1.4.2
Requires-Dist: matplotlib>=3.9.1
Requires-Dist: numpy<2.0.0,>=1.26.4
Requires-Dist: scipy>=1.14.0
Requires-Dist: tqdm>=4.66.5
Requires-Dist: typing-extensions>=4.12.2
